askput/__init__.py
askput/core.py
askput/validators.py
askput-0.1.5.dist-info/licenses/LICENSE
askput-0.1.5.dist-info/METADATA
askput-0.1.5.dist-info/WHEEL
askput-0.1.5.dist-info/top_level.txt
askput-0.1.5.dist-info/RECORD
