Metadata-Version: 2.4
Name: askput
Version: 0.1.5
Summary: Simple and safe console input validation for Python
Author-email: Basil S <bbbbasil1739@gmail.com>
Maintainer-email: Basil S <bbbbasil1739@gmail.com>
License: MIT
Project-URL: Homepage, https://github.com/1-basil/askput
Project-URL: Repository, https://github.com/1-basil/askput
Project-URL: Documentation, https://github.com/1-basil/askput#readme
Project-URL: Bug Tracker, https://github.com/1-basil/askput/issues
Project-URL: Changelog, https://github.com/1-basil/askput/releases
Keywords: input,validation,console,cli,user-input,type-checking,input-validation,beginner-friendly,safe-input,askput
Classifier: Development Status :: 4 - Beta
Classifier: Intended Audience :: Developers
Classifier: Intended Audience :: Education
Classifier: Topic :: Software Development :: Libraries :: Python Modules
Classifier: Topic :: Utilities
Classifier: License :: OSI Approved :: MIT License
Classifier: Operating System :: OS Independent
Classifier: Programming Language :: Python :: 3
Classifier: Programming Language :: Python :: 3.8
Classifier: Programming Language :: Python :: 3.9
Classifier: Programming Language :: Python :: 3.10
Classifier: Programming Language :: Python :: 3.11
Classifier: Programming Language :: Python :: 3.12
Classifier: Typing :: Typed
Classifier: Environment :: Console
Requires-Python: >=3.8
License-File: LICENSE
Provides-Extra: dev
Requires-Dist: pytest>=7.0; extra == "dev"
Requires-Dist: black>=23.0; extra == "dev"
Requires-Dist: mypy>=1.0; extra == "dev"
Dynamic: license-file
